vnpy_mt5/__init__.py
vnpy_mt5/mt5_gateway.py
vnpy_mt5-2024.3.12.dist-info/LICENSE
vnpy_mt5-2024.3.12.dist-info/METADATA
vnpy_mt5-2024.3.12.dist-info/WHEEL
vnpy_mt5-2024.3.12.dist-info/top_level.txt
vnpy_mt5-2024.3.12.dist-info/RECORD
