Metadata-Version: 2.1
Name: vnpy-mt5
Version: 2024.3.12
Summary: MT5 trading gateway for VeighNa Evo.
Home-page: https://www.github.com/veighna-global
Author: VeighNa Global
Author-email: veighna@hotmail.com
License: MIT
Keywords: quant,quantitative,investment,trading,algotrading,mt5
Classifier: Development Status :: 5 - Production/Stable
Classifier: Operating System :: OS Independent
Classifier: Programming Language :: Python :: 3
Classifier: Programming Language :: Python :: 3.10
Classifier: Programming Language :: Python :: 3.11
Classifier: Programming Language :: Python :: 3.12
Classifier: Topic :: Office/Business :: Financial :: Investment
Classifier: Programming Language :: Python :: Implementation :: CPython
Classifier: License :: OSI Approved :: MIT License
Classifier: Natural Language :: English
License-File: LICENSE
